gabapi/__init__.py
gabapi/gabapi.py
gabapi-0.0.3.dist-info/METADATA
gabapi-0.0.3.dist-info/RECORD
gabapi-0.0.3.dist-info/WHEEL
gabapi-0.0.3.dist-info/top_level.txt
