Metadata-Version: 2.1
Name: gabapi
Version: 0.0.3
Summary: Provides access to Gab REST API
Home-page: http://github.com/undeadmockingbird/AltTech
Author: Undead Mockingbird
Author-email: undeadmockingbird@protonmail.com
License: MIT
Platform: UNKNOWN
